<Class>
    <Id>122</Id>
    <ClassName>magicsquares</ClassName>
    <SuperClass></SuperClass>
    <SuperInterfaceList>
        <SuperInterface></SuperInterface>
    </SuperInterfaceList>
    <ClassComment></ClassComment>
    <FieldList>
        <Field>
            <FieldName>n</FieldName>
            <FieldType>int</FieldType>
        </Field>
        <Field>
            <FieldName>mn</FieldName>
            <FieldType>int</FieldType>
        </Field>
        <Field>
            <FieldName>x</FieldName>
            <FieldType>int</FieldType>
        </Field>
        <Field>
            <FieldName>y</FieldName>
            <FieldType>int</FieldType>
        </Field>
        <Field>
            <FieldName>moves</FieldName>
            <FieldType>int[]</FieldType>
        </Field>
        <Field>
            <FieldName>grid</FieldName>
            <FieldType>int[]</FieldType>
        </Field>
        <Field>
            <FieldName>priorityCalculated</FieldName>
            <FieldType>boolean</FieldType>
        </Field>
        <Field>
            <FieldName>priority</FieldName>
            <FieldType>int</FieldType>
        </Field>
        <Field>
            <FieldName>ffm</FieldName>
            <FieldType>FfmResult</FieldType>
        </Field>
    </FieldList>
    <MethodList>
        <Method>
            <MethodName>FfmResult</MethodName>
            <MethodComment></MethodComment>
            <ReturnType></ReturnType>
            <ParameterList>
                <Parameter>
                    <ParamName>ix</ParamName>
                    <ParamType>int</ParamType>
                </Parameter>
                <Parameter>
                    <ParamName>iy</ParamName>
                    <ParamType>int</ParamType>
                </Parameter>
                <Parameter>
                    <ParamName>imoves</ParamName>
                    <ParamType>int[]</ParamType>
                </Parameter>
            </ParameterList>
            <InnerVarList>
                <InnerVar></InnerVar>
            </InnerVarList>
            <InnerMethodInvokeList>
                <InnerMethodInvoke></InnerMethodInvoke>
            </InnerMethodInvokeList>
            <ThrowExceptionList>
                <ExceptionType></ExceptionType>
            </ThrowExceptionList>
        </Method>
        <Method>
            <MethodName>PQNode</MethodName>
            <MethodComment></MethodComment>
            <ReturnType></ReturnType>
            <ParameterList/>
            <InnerVarList>
                <InnerVar>int [i]</InnerVar>
            </InnerVarList>
            <InnerMethodInvokeList>
                <InnerMethodInvoke></InnerMethodInvoke>
            </InnerMethodInvokeList>
            <ThrowExceptionList>
                <ExceptionType></ExceptionType>
            </ThrowExceptionList>
        </Method>
        <Method>
            <MethodName>PQNode</MethodName>
            <MethodComment></MethodComment>
            <ReturnType></ReturnType>
            <ParameterList>
                <Parameter>
                    <ParamName>other</ParamName>
                    <ParamType>PQNode</ParamType>
                </Parameter>
            </ParameterList>
            <InnerVarList>
                <InnerVar></InnerVar>
            </InnerVarList>
            <InnerMethodInvokeList>
                <InnerMethodInvoke></InnerMethodInvoke>
            </InnerMethodInvokeList>
            <ThrowExceptionList>
                <ExceptionType></ExceptionType>
            </ThrowExceptionList>
        </Method>
        <Method>
            <MethodName>gridRow</MethodName>
            <MethodComment></MethodComment>
            <ReturnType>int[]</ReturnType>
            <ParameterList>
                <Parameter>
                    <ParamName>y</ParamName>
                    <ParamType>int</ParamType>
                </Parameter>
            </ParameterList>
            <InnerVarList>
                <InnerVar>int[] [r=new int[n]]</InnerVar>
                <InnerVar>int [x]</InnerVar>
            </InnerVarList>
            <InnerMethodInvokeList>
                <InnerMethodInvoke></InnerMethodInvoke>
            </InnerMethodInvokeList>
            <ThrowExceptionList>
                <ExceptionType></ExceptionType>
            </ThrowExceptionList>
        </Method>
        <Method>
            <MethodName>gridCol</MethodName>
            <MethodComment></MethodComment>
            <ReturnType>int[]</ReturnType>
            <ParameterList>
                <Parameter>
                    <ParamName>x</ParamName>
                    <ParamType>int</ParamType>
                </Parameter>
            </ParameterList>
            <InnerVarList>
                <InnerVar>int[] [r=new int[n]]</InnerVar>
                <InnerVar>int [y]</InnerVar>
            </InnerVarList>
            <InnerMethodInvokeList>
                <InnerMethodInvoke></InnerMethodInvoke>
            </InnerMethodInvokeList>
            <ThrowExceptionList>
                <ExceptionType></ExceptionType>
            </ThrowExceptionList>
        </Method>
        <Method>
            <MethodName>diagonal</MethodName>
            <MethodComment></MethodComment>
            <ReturnType>int[]</ReturnType>
            <ParameterList>
                <Parameter>
                    <ParamName>q</ParamName>
                    <ParamType>int</ParamType>
                </Parameter>
            </ParameterList>
            <InnerVarList>
                <InnerVar>int[] [r=new int[n]]</InnerVar>
                <InnerVar>int [i]</InnerVar>
            </InnerVarList>
            <InnerMethodInvokeList>
                <InnerMethodInvoke></InnerMethodInvoke>
            </InnerMethodInvokeList>
            <ThrowExceptionList>
                <ExceptionType></ExceptionType>
            </ThrowExceptionList>
        </Method>
        <Method>
            <MethodName>possibleMoves</MethodName>
            <MethodComment></MethodComment>
            <ReturnType>int[]</ReturnType>
            <ParameterList>
                <Parameter>
                    <ParamName>x</ParamName>
                    <ParamType>int</ParamType>
                </Parameter>
                <Parameter>
                    <ParamName>y</ParamName>
                    <ParamType>int</ParamType>
                </Parameter>
            </ParameterList>
            <InnerVarList>
                <InnerVar>int [zerocount, sum, highest, j, i]</InnerVar>
                <InnerVar>ArrayList&lt;int[]&gt; [cellGroups=new ArrayList&lt;int[]&gt;()]</InnerVar>
                <InnerVar>HashSet&lt;Integer&gt; [usedNumbers=new HashSet&lt;Integer&gt;()]</InnerVar>
                <InnerVar>HashSet&lt;Integer&gt; [onePossible=new HashSet&lt;Integer&gt;()]</InnerVar>
                <InnerVar>ArrayList&lt;Integer&gt; [moves=new ArrayList&lt;Integer&gt;()]</InnerVar>
                <InnerVar>int[] [r=new int[moves.size()]]</InnerVar>
            </InnerVarList>
            <InnerMethodInvokeList>
                <InnerMethodInvoke>cellGroups;add;[gridCol(x)]</InnerMethodInvoke>
                <InnerMethodInvoke>cellGroups;add;[gridRow(y)]</InnerMethodInvoke>
            </InnerMethodInvokeList>
            <ThrowExceptionList>
                <ExceptionType></ExceptionType>
            </ThrowExceptionList>
        </Method>
        <Method>
            <MethodName>findFewestMoves</MethodName>
            <MethodComment></MethodComment>
            <ReturnType>FfmResult</ReturnType>
            <ParameterList/>
            <InnerVarList>
                <InnerVar>int [x, y, mx, my, ind]</InnerVar>
                <InnerVar>int[] [minmoves=(new int[]{})]</InnerVar>
                <InnerVar>int[] [moves]</InnerVar>
            </InnerVarList>
            <InnerMethodInvokeList>
                <InnerMethodInvoke></InnerMethodInvoke>
            </InnerMethodInvokeList>
            <ThrowExceptionList>
                <ExceptionType></ExceptionType>
            </ThrowExceptionList>
        </Method>
        <Method>
            <MethodName>calculatePriority</MethodName>
            <MethodComment></MethodComment>
            <ReturnType>void</ReturnType>
            <ParameterList/>
            <InnerVarList>
                <InnerVar>int [i, zerocount]</InnerVar>
            </InnerVarList>
            <InnerMethodInvokeList>
                <InnerMethodInvoke></InnerMethodInvoke>
            </InnerMethodInvokeList>
            <ThrowExceptionList>
                <ExceptionType></ExceptionType>
            </ThrowExceptionList>
        </Method>
        <Method>
            <MethodName>getPriority</MethodName>
            <MethodComment></MethodComment>
            <ReturnType>int</ReturnType>
            <ParameterList/>
            <InnerVarList>
                <InnerVar></InnerVar>
            </InnerVarList>
            <InnerMethodInvokeList>
                <InnerMethodInvoke></InnerMethodInvoke>
            </InnerMethodInvokeList>
            <ThrowExceptionList>
                <ExceptionType></ExceptionType>
            </ThrowExceptionList>
        </Method>
        <Method>
            <MethodName>compareTo</MethodName>
            <MethodComment></MethodComment>
            <ReturnType>int</ReturnType>
            <ParameterList>
                <Parameter>
                    <ParamName>anotherMSquare</ParamName>
                    <ParamType>Object</ParamType>
                </Parameter>
            </ParameterList>
            <InnerVarList>
                <InnerVar>PQNode [other=(PQNode)anotherMSquare]</InnerVar>
                <InnerVar>int [c=getPriority() - other.getPriority()]</InnerVar>
            </InnerVarList>
            <InnerMethodInvokeList>
                <InnerMethodInvoke></InnerMethodInvoke>
            </InnerMethodInvokeList>
            <ThrowExceptionList>
                <ExceptionType>ClassCastException</ExceptionType>
            </ThrowExceptionList>
        </Method>
        <Method>
            <MethodName>toString</MethodName>
            <MethodComment></MethodComment>
            <ReturnType>String</ReturnType>
            <ParameterList/>
            <InnerVarList>
                <InnerVar>StringBuilder [sb=new StringBuilder()]</InnerVar>
                <InnerVar>int [y, x]</InnerVar>
            </InnerVarList>
            <InnerMethodInvokeList>
                <InnerMethodInvoke></InnerMethodInvoke>
            </InnerMethodInvokeList>
            <ThrowExceptionList>
                <ExceptionType></ExceptionType>
            </ThrowExceptionList>
        </Method>
        <Method>
            <MethodName>magicsquares</MethodName>
            <MethodComment></MethodComment>
            <ReturnType></ReturnType>
            <ParameterList/>
            <InnerVarList>
                <InnerVar></InnerVar>
            </InnerVarList>
            <InnerMethodInvokeList>
                <InnerMethodInvoke></InnerMethodInvoke>
            </InnerMethodInvokeList>
            <ThrowExceptionList>
                <ExceptionType></ExceptionType>
            </ThrowExceptionList>
        </Method>
        <Method>
            <MethodName>main</MethodName>
            <MethodComment></MethodComment>
            <ReturnType>void</ReturnType>
            <ParameterList>
                <Parameter>
                    <ParamName>args</ParamName>
                    <ParamType>String[]</ParamType>
                </Parameter>
            </ParameterList>
            <InnerVarList>
                <InnerVar>PriorityQueue&lt;magicsquares.PQNode&gt; [pq=new PriorityQueue&lt;magicsquares.PQNode&gt;()]</InnerVar>
            </InnerVarList>
            <InnerMethodInvokeList>
                <InnerMethodInvoke>pq;offer;[new magicsquares.PQNode()]</InnerMethodInvoke>
            </InnerMethodInvokeList>
            <ThrowExceptionList>
                <ExceptionType></ExceptionType>
            </ThrowExceptionList>
        </Method>
    </MethodList>
</Class>